gaea_lae_api.py
GAEA_API-0.0.2.dist-info/METADATA
GAEA_API-0.0.2.dist-info/WHEEL
GAEA_API-0.0.2.dist-info/top_level.txt
GAEA_API-0.0.2.dist-info/RECORD
